README.md
setup.cfg
setup.py
polyfil/__init__.py
polyfil.egg-info/PKG-INFO
polyfil.egg-info/SOURCES.txt
polyfil.egg-info/dependency_links.txt
polyfil.egg-info/requires.txt
polyfil.egg-info/top_level.txt