Metadata-Version: 1.1
Name: polyfil
Version: 0.8
Summary: A random test lib
Home-page: https://github.com/laformarua/polyfil
Author: laformarua
Author-email: lcrua@utp.edu.co
License: UNKNOWN
Download-URL: https://github.com/laformarua/polyfil/archive/0.8.tar.gz
Keywords: testing,logging,example
Platform: UNKNOWN
